bowcar/__init__.py
bowcar/__version__.py
bowcar/base.py
bowcar/live.py
bowcar/upload.py
bowcar/firmware/bowCarForPython_V1.0.0/bowCarForPython_V1.0.0.ino
bowcar-1.1.0.dist-info/METADATA
bowcar-1.1.0.dist-info/WHEEL
bowcar-1.1.0.dist-info/RECORD
