Metadata-Version: 2.4
Name: bowcar
Version: 1.1.0
Summary: A Python module to generate Arduino code for BowCar.
Author-email: ITPLE <itple@itpleinfo.com>
Requires-Python: >=3.8
Requires-Dist: pyserial>=3.0
